kdNLP/__init__.py
KDNLP-0.0.3.dist-info/LICENSE
KDNLP-0.0.3.dist-info/METADATA
KDNLP-0.0.3.dist-info/WHEEL
KDNLP-0.0.3.dist-info/top_level.txt
KDNLP-0.0.3.dist-info/RECORD
