Metadata-Version: 2.1
Name: KDNLP
Version: 0.0.3
Summary: kdNLP: Deep Learning Toolkit for NLP, developed by KDNLP Team
Home-page: UNKNOWN
Author: KDNLP
License: Apache License
Platform: UNKNOWN
Requires-Python: >=3.6
